amselpy/__init__.py
amselpy/amsel.py
amselpy/connection.py
amselpy/skills.py
amselpy/utils.py
amselpy-0.1.8.dist-info/LICENSE
amselpy-0.1.8.dist-info/METADATA
amselpy-0.1.8.dist-info/WHEEL
amselpy-0.1.8.dist-info/top_level.txt
amselpy-0.1.8.dist-info/RECORD
