Metadata-Version: 2.1
Name: amselpy
Version: 0.1.8
Summary: Take control of you Amsel bot.
Home-page: https://github.com/baumeise/amselpy.git
Author: Moritz Gut
Author-email: hello@moritzgut.de
License: UNKNOWN
Platform: UNKNOWN
Classifier: Programming Language :: Python :: 3
Classifier: License :: OSI Approved :: MIT License
Classifier: Operating System :: OS Independent
Requires-Python: >=3.6
